gui.py
iannix.py
image.py
markov.py
midi.py
music.py
osc.py
timer.py
zipf.py
CreativePython/RealtimeAudioPlayer.py
CreativePython/__init__.py
CreativePython/notationRenderer.py
CreativePython/nevmuse/RunMetrics.py
CreativePython/nevmuse/Surveyor.py
CreativePython/nevmuse/__init__.py
CreativePython/nevmuse/Java-Comparison-Tests/advMetricRunner.pythonSurvey.py
CreativePython/nevmuse/Java-Comparison-Tests/compareMetrics_Java-Vs-Python.py
CreativePython/nevmuse/data/Confidence.py
CreativePython/nevmuse/data/Contig.py
CreativePython/nevmuse/data/ExtendedNote.py
CreativePython/nevmuse/data/Histogram.py
CreativePython/nevmuse/data/Judgement.py
CreativePython/nevmuse/data/Measurement.py
CreativePython/nevmuse/data/PianoRoll.py
CreativePython/nevmuse/data/PianoRollOld.py
CreativePython/nevmuse/data/__init__.py
CreativePython/nevmuse/data/test_ExtendedNote.py
CreativePython/nevmuse/data/test_Histogram.py
CreativePython/nevmuse/data/test_Measurement.py
CreativePython/nevmuse/data/test_PianoRoll_assertions.py
CreativePython/nevmuse/data/test_PianoRoll_integration.py
CreativePython/nevmuse/data/test_PianoRoll_quantization.py
CreativePython/nevmuse/data/test_PianoRoll_unit.py
CreativePython/nevmuse/metrics/Metric.py
CreativePython/nevmuse/metrics/ZipfMetrics.py
CreativePython/nevmuse/metrics/__init__.py
CreativePython/nevmuse/metrics/test_Metric.py
CreativePython/nevmuse/metrics/simple/ChordDensityMetric.py
CreativePython/nevmuse/metrics/simple/ChordDistanceMetric.py
CreativePython/nevmuse/metrics/simple/ChordMetric.py
CreativePython/nevmuse/metrics/simple/ChordNormalizedMetric.py
CreativePython/nevmuse/metrics/simple/ChromaticToneMetric.py
CreativePython/nevmuse/metrics/simple/ContourBasslineDurationMetric.py
CreativePython/nevmuse/metrics/simple/ContourBasslineDurationQuantizedMetric.py
CreativePython/nevmuse/metrics/simple/ContourBasslinePitchMetric.py
CreativePython/nevmuse/metrics/simple/ContourMelodyDurationMetric.py
creativepython-0.3.6.dist-info/licenses/LICENSE
creativepython-0.3.6.dist-info/licenses/LICENSE-PSF
creativepython-0.3.6.dist-info/METADATA
creativepython-0.3.6.dist-info/WHEEL
creativepython-0.3.6.dist-info/top_level.txt
creativepython-0.3.6.dist-info/RECORD
