Metadata-Version: 2.4
Name: CreativePython
Version: 0.3.6
Summary: A Python-based software environment for developing algorithmic art projects.
Author-email: "Dr. Bill Manaris" <manaris@cofc.edu>, Taj Ballinger <ballingertj@g.cofc.edu>, Trevor Ritchie <ritchiets@g.cofc.edu>
License: MIT License
Project-URL: Homepage, https://jythonmusic.me
Keywords: music,audio,midi,learning,algorithmic art,algoart
Classifier: Programming Language :: Python :: 3
Classifier: Operating System :: OS Independent
Classifier: License :: OSI Approved :: MIT License
Requires-Python: >=3.9
License-File: LICENSE
License-File: LICENSE-PSF
Requires-Dist: setuptools>=69.0
Requires-Dist: tinysoundfont>=0.3.6
Requires-Dist: osc4py3>=1.0.8
Requires-Dist: mido>=1.3.3
Requires-Dist: PySide6>=6.9.1
Requires-Dist: python-rtmidi>=1.5.8
Requires-Dist: sounddevice>=0.5.2
Requires-Dist: soundfile>=0.13.1
Requires-Dist: tqdm>=4.67.1
Requires-Dist: pooch>=1.8
Requires-Dist: pypianoroll>=1.0
Requires-Dist: verovio>=5.6.0
Requires-Dist: pymusicxml>=0.5.6
Provides-Extra: dev
Requires-Dist: build; extra == "dev"
Requires-Dist: twine; extra == "dev"
Dynamic: license-file
